logflux/__init__.py
logflux/batch.py
logflux/client.py
logflux/config.py
logflux/types.py
logflux/integrations/__init__.py
logflux/integrations/logging_handler.py
logflux_io-0.1.0b0.dist-info/licenses/LICENSE-APACHE-2.0
logflux_io-0.1.0b0.dist-info/METADATA
logflux_io-0.1.0b0.dist-info/WHEEL
logflux_io-0.1.0b0.dist-info/top_level.txt
logflux_io-0.1.0b0.dist-info/RECORD
