Metadata-Version: 2.4
Name: logflux-io
Version: 0.1.0b0
Summary: A lightweight Python SDK for LogFlux agent communication
Author-email: LogFlux Team <support@logflux.io>
License: Apache-2.0
Project-URL: Homepage, https://github.com/logflux-io/logflux-python-sdk
Project-URL: Documentation, https://docs.logflux.io
Project-URL: Repository, https://github.com/logflux-io/logflux-python-sdk
Project-URL: Bug Tracker, https://github.com/logflux-io/logflux-python-sdk/issues
Keywords: logflux,logging,telemetry,monitoring,observability
Classifier: Development Status :: 4 - Beta
Classifier: Intended Audience :: Developers
Classifier: Operating System :: OS Independent
Classifier: Programming Language :: Python :: 3
Classifier: Programming Language :: Python :: 3.8
Classifier: Programming Language :: Python :: 3.9
Classifier: Programming Language :: Python :: 3.10
Classifier: Programming Language :: Python :: 3.11
Classifier: Programming Language :: Python :: 3.12
Classifier: Topic :: Software Development :: Libraries :: Python Modules
Classifier: Topic :: System :: Logging
Classifier: Topic :: System :: Monitoring
Requires-Python: >=3.8
License-File: LICENSE-APACHE-2.0
Provides-Extra: dev
Requires-Dist: pytest>=6.0.0; extra == "dev"
Requires-Dist: pytest-cov>=2.10.0; extra == "dev"
Requires-Dist: black>=21.0.0; extra == "dev"
Requires-Dist: flake8>=3.8.0; extra == "dev"
Requires-Dist: mypy>=0.800; extra == "dev"
Requires-Dist: isort>=5.0.0; extra == "dev"
Provides-Extra: test
Requires-Dist: pytest>=6.0.0; extra == "test"
Requires-Dist: pytest-cov>=2.10.0; extra == "test"
Dynamic: license-file
